ai_stepper/__init__.py
ai_stepper/ai_stepper.py
ai_stepper/schema/__init__.py
ai_stepper/schema/callback.py
ai_stepper/schema/output_validation_error.py
ai_stepper/schema/step.py
ai_stepper/schema/workflow_execution_result.py
ai_stepper/utils/__init__.py
ai_stepper/utils/logger.py
ai_stepper/utils/retry.py
ai_stepper-0.1.4.dist-info/LICENSE
ai_stepper-0.1.4.dist-info/METADATA
ai_stepper-0.1.4.dist-info/WHEEL
ai_stepper-0.1.4.dist-info/top_level.txt
ai_stepper-0.1.4.dist-info/RECORD
