Metadata-Version: 2.1
Name: ai-stepper
Version: 0.1.4
Summary: A flexible Python framework for creating step-by-step AI workflows
Home-page: https://github.com/alfredwallace7/ai-stepper
Author: alfredwallace7
Author-email: alfred.wallace@netcraft.fr
Classifier: Development Status :: 3 - Alpha
Classifier: Intended Audience :: Developers
Classifier: License :: OSI Approved :: MIT License
Classifier: Operating System :: OS Independent
Classifier: Programming Language :: Python :: 3
Classifier: Programming Language :: Python :: 3.8
Classifier: Programming Language :: Python :: 3.9
Classifier: Programming Language :: Python :: 3.10
Classifier: Programming Language :: Python :: 3.11
Requires-Python: >=3.8
License-File: LICENSE
Requires-Dist: litellm==1.55.3
Requires-Dist: pydantic==2.10.1
Requires-Dist: PyYAML==6.0.2
Requires-Dist: python-dotenv==1.0.1
Requires-Dist: jsonschema==4.23.0
Requires-Dist: rich==13.9.4
Requires-Dist: tiktoken==0.8.0
Requires-Dist: pytz==2024.2
